buffering_smtp_handler.py
setup.py
buffering_smtp_handler.egg-info/PKG-INFO
buffering_smtp_handler.egg-info/SOURCES.txt
buffering_smtp_handler.egg-info/dependency_links.txt
buffering_smtp_handler.egg-info/top_level.txt