Metadata-Version: 1.1
Name: buffering-smtp-handler
Version: 0.2
Summary: Enables sending multiple logging events in a single email
Home-page: https://github.com/mike-charles/python-buffering-smtp-handler
Author: Mike Charles
Author-email: mike.e.charles@gmail.com
License: UNKNOWN
Platform: UNKNOWN
Classifier: Programming Language :: Python :: 2
Classifier: Programming Language :: Python :: 3
Classifier: Intended Audience :: Developers
Classifier: Topic :: Software Development :: Libraries
Classifier: Topic :: Utilities
